[{
  "item": "P560",
  "h": 65,
  "a": null,
  "b": null,
  "r": 60,
  "mat": "D",
  "matdef": "D",
  "a2": null,
  "b2": null,
  "r2": 40,
  "oak": 1,
  "beech": null,
  "birch": null,
  "pine": null,
  "coveroakru": "Масло, натуральный воск",
  "coveroaken": "Decorative impregnating oil, natural wax",
  "coverbeechru": "Масло, натуральный воск",
  "coverbeechen": "Decorative impregnating oil, natural wax",
  "coverbirchru": "Шлифовка",
  "coverbirchen": "Grinding",
  "coverpineru": "Шлифовка",
  "coverpineen": "Grinding",
  "alt": "P560",
  "promoru": "Новинка",
  "promoen": "New",
  "descriptionru": null,
  "descriptionen": null
}, {
  "item": "P560C",
  "h": 85,
  "a": null,
  "b": null,
  "r": 60,
  "mat": "D",
  "matdef": "D",
  "a2": null,
  "b2": null,
  "r2": 55,
  "oak": 1,
  "beech": null,
  "birch": null,
  "pine": null,
  "coveroakru": "Масло, натуральный воск",
  "coveroaken": "Decorative impregnating oil, natural wax",
  "coverbeechru": "Масло, натуральный воск",
  "coverbeechen": "Decorative impregnating oil, natural wax",
  "coverbirchru": "Шлифовка",
  "coverbirchen": "Grinding",
  "coverpineru": "Шлифовка",
  "coverpineen": "Grinding",
  "alt": "P560С",
  "promoru": "Новинка",
  "promoen": "New",
  "descriptionru": null,
  "descriptionen": null
}, {
  "item": "P460",
  "h": 65,
  "a": 60,
  "b": 60,
  "r": null,
  "mat": "D",
  "matdef": "D",
  "a2": 40,
  "b2": 40,
  "r2": null,
  "oak": 1,
  "beech": null,
  "birch": null,
  "pine": null,
  "coveroakru": "Масло, натуральный воск",
  "coveroaken": "Decorative impregnating oil, natural wax",
  "coverbeechru": "Масло, натуральный воск",
  "coverbeechen": "Decorative impregnating oil, natural wax",
  "coverbirchru": "Шлифовка",
  "coverbirchen": "Grinding",
  "coverpineru": "Шлифовка",
  "coverpineen": "Grinding",
  "alt": "P460",
  "promoru": "Новинка",
  "promoen": "New",
  "descriptionru": null,
  "descriptionen": null
}, {
  "item": "P460C",
  "h": 85,
  "a": 60,
  "b": 60,
  "r": null,
  "mat": "D",
  "matdef": "D",
  "a2": 57,
  "b2": 39,
  "r2": null,
  "oak": 1,
  "beech": null,
  "birch": null,
  "pine": null,
  "coveroakru": "Масло, натуральный воск",
  "coveroaken": "Decorative impregnating oil, natural wax",
  "coverbeechru": "Масло, натуральный воск",
  "coverbeechen": "Decorative impregnating oil, natural wax",
  "coverbirchru": "Шлифовка",
  "coverbirchen": "Grinding",
  "coverpineru": "Шлифовка",
  "coverpineen": "Grinding",
  "alt": "P460С",
  "promoru": "Новинка",
  "promoen": "New",
  "descriptionru": null,
  "descriptionen": null
}, {
  "item": "R160",
  "h": 14,
  "a": null,
  "b": null,
  "r": 60,
  "mat": "D",
  "matdef": "D",
  "a2": null,
  "b2": null,
  "r2": 50,
  "oak": 1,
  "beech": 1,
  "birch": null,
  "pine": 1,
  "coveroakru": "Масло, натуральный воск",
  "coveroaken": "Decorative impregnating oil, natural wax",
  "coverbeechru": "Масло, натуральный воск",
  "coverbeechen": "Decorative impregnating oil, natural wax",
  "coverbirchru": "Шлифовка",
  "coverbirchen": "Grinding",
  "coverpineru": "Шлифовка",
  "coverpineen": "Grinding",
  "alt": "R160",
  "promoru": null,
  "promoen": null,
  "descriptionru": null,
  "descriptionen": null
}, {
  "item": "R260",
  "h": 14,
  "a": null,
  "b": null,
  "r": 60,
  "mat": "B",
  "matdef": "B",
  "a2": null,
  "b2": null,
  "r2": 50,
  "oak": null,
  "beech": 1,
  "birch": null,
  "pine": 1,
  "coveroakru": "Масло, натуральный воск",
  "coveroaken": "Decorative impregnating oil, natural wax",
  "coverbeechru": "Масло, натуральный воск",
  "coverbeechen": "Decorative impregnating oil, natural wax",
  "coverbirchru": "Шлифовка",
  "coverbirchen": "Grinding",
  "coverpineru": "Шлифовка",
  "coverpineen": "Grinding",
  "alt": "R260",
  "promoru": null,
  "promoen": null,
  "descriptionru": null,
  "descriptionen": null
}, {
  "item": "R360",
  "h": 14,
  "a": null,
  "b": null,
  "r": 60,
  "mat": "B",
  "matdef": "B",
  "a2": null,
  "b2": null,
  "r2": 50,
  "oak": null,
  "beech": 1,
  "birch": null,
  "pine": 1,
  "coveroakru": "Масло, натуральный воск",
  "coveroaken": "Decorative impregnating oil, natural wax",
  "coverbeechru": "Масло, натуральный воск",
  "coverbeechen": "Decorative impregnating oil, natural wax",
  "coverbirchru": "Шлифовка",
  "coverbirchen": "Grinding",
  "coverpineru": "Шлифовка",
  "coverpineen": "Grinding",
  "alt": "R360",
  "promoru": null,
  "promoen": null,
  "descriptionru": null,
  "descriptionen": null
}, {
  "item": "R460",
  "h": 14,
  "a": null,
  "b": null,
  "r": 60,
  "mat": "D",
  "matdef": "D",
  "a2": null,
  "b2": null,
  "r2": 50,
  "oak": 1,
  "beech": 1,
  "birch": null,
  "pine": 1,
  "coveroakru": "Масло, натуральный воск",
  "coveroaken": "Decorative impregnating oil, natural wax",
  "coverbeechru": "Масло, натуральный воск",
  "coverbeechen": "Decorative impregnating oil, natural wax",
  "coverbirchru": "Шлифовка",
  "coverbirchen": "Grinding",
  "coverpineru": "Шлифовка",
  "coverpineen": "Grinding",
  "alt": "R460",
  "promoru": "Новинка",
  "promoen": "New",
  "descriptionru": null,
  "descriptionen": null
}, {
  "item": "R560",
  "h": 14,
  "a": null,
  "b": null,
  "r": 60,
  "mat": "D",
  "matdef": "D",
  "a2": null,
  "b2": null,
  "r2": 45,
  "oak": 1,
  "beech": 1,
  "birch": null,
  "pine": null,
  "coveroakru": "Масло, натуральный воск",
  "coveroaken": "Decorative impregnating oil, natural wax",
  "coverbeechru": "Масло, натуральный воск",
  "coverbeechen": "Decorative impregnating oil, natural wax",
  "coverbirchru": "Шлифовка",
  "coverbirchen": "Grinding",
  "coverpineru": "Шлифовка",
  "coverpineen": "Grinding",
  "alt": "R560",
  "promoru": "Новинка",
  "promoen": "New",
  "descriptionru": null,
  "descriptionen": null
}, {
  "item": "R170",
  "h": 17,
  "a": null,
  "b": null,
  "r": 70,
  "mat": "D",
  "matdef": "D",
  "a2": null,
  "b2": null,
  "r2": 60,
  "oak": 1,
  "beech": 1,
  "birch": null,
  "pine": 1,
  "coveroakru": "Масло, натуральный воск",
  "coveroaken": "Decorative impregnating oil, natural wax",
  "coverbeechru": "Масло, натуральный воск",
  "coverbeechen": "Decorative impregnating oil, natural wax",
  "coverbirchru": "Шлифовка",
  "coverbirchen": "Grinding",
  "coverpineru": "Шлифовка",
  "coverpineen": "Grinding",
  "alt": "R170",
  "promoru": null,
  "promoen": null,
  "descriptionru": null,
  "descriptionen": null
}, {
  "item": "R270",
  "h": 18,
  "a": null,
  "b": null,
  "r": 70,
  "mat": "B",
  "matdef": "B",
  "a2": null,
  "b2": null,
  "r2": 60,
  "oak": null,
  "beech": 1,
  "birch": null,
  "pine": 1,
  "coveroakru": "Масло, натуральный воск",
  "coveroaken": "Decorative impregnating oil, natural wax",
  "coverbeechru": "Масло, натуральный воск",
  "coverbeechen": "Decorative impregnating oil, natural wax",
  "coverbirchru": "Шлифовка",
  "coverbirchen": "Grinding",
  "coverpineru": "Шлифовка",
  "coverpineen": "Grinding",
  "alt": "R270",
  "promoru": null,
  "promoen": null,
  "descriptionru": null,
  "descriptionen": null
}, {
  "item": "R370",
  "h": 17,
  "a": null,
  "b": null,
  "r": 70,
  "mat": "B",
  "matdef": "B",
  "a2": null,
  "b2": null,
  "r2": 60,
  "oak": null,
  "beech": 1,
  "birch": null,
  "pine": 1,
  "coveroakru": "Масло, натуральный воск",
  "coveroaken": "Decorative impregnating oil, natural wax",
  "coverbeechru": "Масло, натуральный воск",
  "coverbeechen": "Decorative impregnating oil, natural wax",
  "coverbirchru": "Шлифовка",
  "coverbirchen": "Grinding",
  "coverpineru": "Шлифовка",
  "coverpineen": "Grinding",
  "alt": "R370",
  "promoru": null,
  "promoen": null,
  "descriptionru": null,
  "descriptionen": null
}, {
  "item": "R470",
  "h": 17,
  "a": null,
  "b": null,
  "r": 70,
  "mat": "B",
  "matdef": "B",
  "a2": null,
  "b2": null,
  "r2": 60,
  "oak": null,
  "beech": 1,
  "birch": null,
  "pine": 1,
  "coveroakru": "Масло, натуральный воск",
  "coveroaken": "Decorative impregnating oil, natural wax",
  "coverbeechru": "Масло, натуральный воск",
  "coverbeechen": "Decorative impregnating oil, natural wax",
  "coverbirchru": "Шлифовка",
  "coverbirchen": "Grinding",
  "coverpineru": "Шлифовка",
  "coverpineen": "Grinding",
  "alt": "R470",
  "promoru": null,
  "promoen": null,
  "descriptionru": null,
  "descriptionen": null
}, {
  "item": "R570",
  "h": 17,
  "a": null,
  "b": null,
  "r": 70,
  "mat": "B",
  "matdef": "B",
  "a2": null,
  "b2": null,
  "r2": 50,
  "oak": null,
  "beech": 1,
  "birch": null,
  "pine": null,
  "coveroakru": "Масло, натуральный воск",
  "coveroaken": "Decorative impregnating oil, natural wax",
  "coverbeechru": "Масло, натуральный воск",
  "coverbeechen": "Decorative impregnating oil, natural wax",
  "coverbirchru": "Шлифовка",
  "coverbirchen": "Grinding",
  "coverpineru": "Шлифовка",
  "coverpineen": "Grinding",
  "alt": "R570",
  "promoru": "Новинка",
  "promoen": "New",
  "descriptionru": null,
  "descriptionen": null
}, {
  "item": "R180",
  "h": 19,
  "a": null,
  "b": null,
  "r": 80,
  "mat": "D",
  "matdef": "D",
  "a2": null,
  "b2": null,
  "r2": 70,
  "oak": 1,
  "beech": 1,
  "birch": null,
  "pine": 1,
  "coveroakru": "Масло, натуральный воск",
  "coveroaken": "Decorative impregnating oil, natural wax",
  "coverbeechru": "Масло, натуральный воск",
  "coverbeechen": "Decorative impregnating oil, natural wax",
  "coverbirchru": "Шлифовка",
  "coverbirchen": "Grinding",
  "coverpineru": "Шлифовка",
  "coverpineen": "Grinding",
  "alt": "R180",
  "promoru": null,
  "promoen": null,
  "descriptionru": null,
  "descriptionen": null
}, {
  "item": "R280",
  "h": 20,
  "a": null,
  "b": null,
  "r": 80,
  "mat": "B",
  "matdef": "B",
  "a2": null,
  "b2": null,
  "r2": 70,
  "oak": null,
  "beech": 1,
  "birch": null,
  "pine": 1,
  "coveroakru": "Масло, натуральный воск",
  "coveroaken": "Decorative impregnating oil, natural wax",
  "coverbeechru": "Масло, натуральный воск",
  "coverbeechen": "Decorative impregnating oil, natural wax",
  "coverbirchru": "Шлифовка",
  "coverbirchen": "Grinding",
  "coverpineru": "Шлифовка",
  "coverpineen": "Grinding",
  "alt": "R280",
  "promoru": null,
  "promoen": null,
  "descriptionru": null,
  "descriptionen": null
}, {
  "item": "R380",
  "h": 19,
  "a": null,
  "b": null,
  "r": 80,
  "mat": "B",
  "matdef": "B",
  "a2": null,
  "b2": null,
  "r2": 70,
  "oak": null,
  "beech": 1,
  "birch": null,
  "pine": 1,
  "coveroakru": "Масло, натуральный воск",
  "coveroaken": "Decorative impregnating oil, natural wax",
  "coverbeechru": "Масло, натуральный воск",
  "coverbeechen": "Decorative impregnating oil, natural wax",
  "coverbirchru": "Шлифовка",
  "coverbirchen": "Grinding",
  "coverpineru": "Шлифовка",
  "coverpineen": "Grinding",
  "alt": "R380",
  "promoru": null,
  "promoen": null,
  "descriptionru": null,
  "descriptionen": null
}, {
  "item": "R480",
  "h": 19,
  "a": null,
  "b": null,
  "r": 80,
  "mat": "B",
  "matdef": "B",
  "a2": null,
  "b2": null,
  "r2": 70,
  "oak": null,
  "beech": 1,
  "birch": null,
  "pine": 1,
  "coveroakru": "Масло, натуральный воск",
  "coveroaken": "Decorative impregnating oil, natural wax",
  "coverbeechru": "Масло, натуральный воск",
  "coverbeechen": "Decorative impregnating oil, natural wax",
  "coverbirchru": "Шлифовка",
  "coverbirchen": "Grinding",
  "coverpineru": "Шлифовка",
  "coverpineen": "Grinding",
  "alt": "R480",
  "promoru": null,
  "promoen": null,
  "descriptionru": null,
  "descriptionen": null
}, {
  "item": "R580",
  "h": 17,
  "a": null,
  "b": null,
  "r": 80,
  "mat": "B",
  "matdef": "B",
  "a2": null,
  "b2": null,
  "r2": 60,
  "oak": null,
  "beech": 1,
  "birch": null,
  "pine": null,
  "coveroakru": "Масло, натуральный воск",
  "coveroaken": "Decorative impregnating oil, natural wax",
  "coverbeechru": "Масло, натуральный воск",
  "coverbeechen": "Decorative impregnating oil, natural wax",
  "coverbirchru": "Шлифовка",
  "coverbirchen": "Grinding",
  "coverpineru": "Шлифовка",
  "coverpineen": "Grinding",
  "alt": "R580",
  "promoru": "Новинка",
  "promoen": "New",
  "descriptionru": null,
  "descriptionen": null
}, {
  "item": "R1120",
  "h": 23,
  "a": null,
  "b": null,
  "r": 120,
  "mat": "D",
  "matdef": "D",
  "a2": null,
  "b2": null,
  "r2": 110,
  "oak": 1,
  "beech": 1,
  "birch": null,
  "pine": 1,
  "coveroakru": "Масло, натуральный воск",
  "coveroaken": "Decorative impregnating oil, natural wax",
  "coverbeechru": "Масло, натуральный воск",
  "coverbeechen": "Decorative impregnating oil, natural wax",
  "coverbirchru": "Шлифовка",
  "coverbirchen": "Grinding",
  "coverpineru": "Шлифовка",
  "coverpineen": "Grinding",
  "alt": "R1120",
  "promoru": null,
  "promoen": null,
  "descriptionru": null,
  "descriptionen": null
}, {
  "item": "R2120",
  "h": 24,
  "a": null,
  "b": null,
  "r": 120,
  "mat": "D",
  "matdef": "D",
  "a2": null,
  "b2": null,
  "r2": 110,
  "oak": 1,
  "beech": 1,
  "birch": null,
  "pine": 1,
  "coveroakru": "Масло, натуральный воск",
  "coveroaken": "Decorative impregnating oil, natural wax",
  "coverbeechru": "Масло, натуральный воск",
  "coverbeechen": "Decorative impregnating oil, natural wax",
  "coverbirchru": "Шлифовка",
  "coverbirchen": "Grinding",
  "coverpineru": "Шлифовка",
  "coverpineen": "Grinding",
  "alt": "R2120",
  "promoru": "Новинка",
  "promoen": "New",
  "descriptionru": null,
  "descriptionen": null
}, {
  "item": "R3120",
  "h": 23,
  "a": null,
  "b": null,
  "r": 120,
  "mat": "B",
  "matdef": "B",
  "a2": null,
  "b2": null,
  "r2": 110,
  "oak": null,
  "beech": 1,
  "birch": null,
  "pine": 1,
  "coveroakru": "Масло, натуральный воск",
  "coveroaken": "Decorative impregnating oil, natural wax",
  "coverbeechru": "Масло, натуральный воск",
  "coverbeechen": "Decorative impregnating oil, natural wax",
  "coverbirchru": "Шлифовка",
  "coverbirchen": "Grinding",
  "coverpineru": "Шлифовка",
  "coverpineen": "Grinding",
  "alt": "R3120",
  "promoru": null,
  "promoen": null,
  "descriptionru": null,
  "descriptionen": null
}, {
  "item": "R4120",
  "h": 23,
  "a": null,
  "b": null,
  "r": 120,
  "mat": "B",
  "matdef": "B",
  "a2": null,
  "b2": null,
  "r2": 110,
  "oak": null,
  "beech": 1,
  "birch": null,
  "pine": 1,
  "coveroakru": "Масло, натуральный воск",
  "coveroaken": "Decorative impregnating oil, natural wax",
  "coverbeechru": "Масло, натуральный воск",
  "coverbeechen": "Decorative impregnating oil, natural wax",
  "coverbirchru": "Шлифовка",
  "coverbirchen": "Grinding",
  "coverpineru": "Шлифовка",
  "coverpineen": "Grinding",
  "alt": "R4120",
  "promoru": null,
  "promoen": null,
  "descriptionru": null,
  "descriptionen": null
}, {
  "item": "R5120",
  "h": 22,
  "a": null,
  "b": null,
  "r": 120,
  "mat": "B",
  "matdef": "B",
  "a2": null,
  "b2": null,
  "r2": 110,
  "oak": null,
  "beech": 1,
  "birch": null,
  "pine": null,
  "coveroakru": "Масло, натуральный воск",
  "coveroaken": "Decorative impregnating oil, natural wax",
  "coverbeechru": "Масло, натуральный воск",
  "coverbeechen": "Decorative impregnating oil, natural wax",
  "coverbirchru": "Шлифовка",
  "coverbirchen": "Grinding",
  "coverpineru": "Шлифовка",
  "coverpineen": "Grinding",
  "alt": "R5120",
  "promoru": "Новинка",
  "promoen": "New",
  "descriptionru": null,
  "descriptionen": null
}, {
  "item": "P130",
  "h": 20,
  "a": null,
  "b": null,
  "r": 30,
  "mat": "D",
  "matdef": "D",
  "a2": null,
  "b2": null,
  "r2": 25,
  "oak": 1,
  "beech": 1,
  "birch": null,
  "pine": 1,
  "coveroakru": "Масло, натуральный воск",
  "coveroaken": "Decorative impregnating oil, natural wax",
  "coverbeechru": "Масло, натуральный воск",
  "coverbeechen": "Decorative impregnating oil, natural wax",
  "coverbirchru": "Шлифовка",
  "coverbirchen": "Grinding",
  "coverpineru": "Шлифовка",
  "coverpineen": "Grinding",
  "alt": "P130",
  "promoru": "Новинка",
  "promoen": "New",
  "descriptionru": null,
  "descriptionen": null
}, {
  "item": "P248",
  "h": 32,
  "a": null,
  "b": null,
  "r": 48,
  "mat": "D",
  "matdef": "D",
  "a2": null,
  "b2": null,
  "r2": 40,
  "oak": 1,
  "beech": 1,
  "birch": null,
  "pine": 1,
  "coveroakru": "Масло, натуральный воск",
  "coveroaken": "Decorative impregnating oil, natural wax",
  "coverbeechru": "Масло, натуральный воск",
  "coverbeechen": "Decorative impregnating oil, natural wax",
  "coverbirchru": "Шлифовка",
  "coverbirchen": "Grinding",
  "coverpineru": "Шлифовка",
  "coverpineen": "Grinding",
  "alt": "P248",
  "promoru": "Новинка",
  "promoen": "New",
  "descriptionru": null,
  "descriptionen": null
}, {
  "item": "P370",
  "h": 45,
  "a": null,
  "b": null,
  "r": 70,
  "mat": "D",
  "matdef": "D",
  "a2": null,
  "b2": null,
  "r2": 60,
  "oak": 1,
  "beech": 1,
  "birch": null,
  "pine": 1,
  "coveroakru": "Масло, натуральный воск",
  "coveroaken": "Decorative impregnating oil, natural wax",
  "coverbeechru": "Масло, натуральный воск",
  "coverbeechen": "Decorative impregnating oil, natural wax",
  "coverbirchru": "Шлифовка",
  "coverbirchen": "Grinding",
  "coverpineru": "Шлифовка",
  "coverpineen": "Grinding",
  "alt": "P370",
  "promoru": "Новинка",
  "promoen": "New",
  "descriptionru": null,
  "descriptionen": null
}, {
  "item": "S16",
  "h": 17,
  "a": 80,
  "b": 80,
  "r": null,
  "mat": "D",
  "matdef": "D",
  "a2": 65,
  "b2": 65,
  "r2": null,
  "oak": 1,
  "beech": 1,
  "birch": 1,
  "pine": 1,
  "coveroakru": "Масло, натуральный воск",
  "coveroaken": "Decorative impregnating oil, natural wax",
  "coverbeechru": "Масло, натуральный воск",
  "coverbeechen": "Decorative impregnating oil, natural wax",
  "coverbirchru": "Шлифовка",
  "coverbirchen": "Grinding",
  "coverpineru": "Шлифовка",
  "coverpineen": "Grinding",
  "alt": "S16",
  "promoru": null,
  "promoen": null,
  "descriptionru": null,
  "descriptionen": null
}, {
  "item": "S112",
  "h": 17,
  "a": 140,
  "b": 100,
  "r": null,
  "mat": "B",
  "matdef": "B",
  "a2": 125,
  "b2": 85,
  "r2": null,
  "oak": null,
  "beech": 1,
  "birch": 1,
  "pine": 1,
  "coveroakru": "Масло, натуральный воск",
  "coveroaken": "Decorative impregnating oil, natural wax",
  "coverbeechru": "Масло, натуральный воск",
  "coverbeechen": "Decorative impregnating oil, natural wax",
  "coverbirchru": "Шлифовка",
  "coverbirchen": "Grinding",
  "coverpineru": "Шлифовка",
  "coverpineen": "Grinding",
  "alt": "S112",
  "promoru": null,
  "promoen": null,
  "descriptionru": null,
  "descriptionen": null
}, {
  "item": "S115",
  "h": 17,
  "a": 170,
  "b": 120,
  "r": null,
  "mat": "B",
  "matdef": "B",
  "a2": 155,
  "b2": 105,
  "r2": null,
  "oak": null,
  "beech": 1,
  "birch": 1,
  "pine": 1,
  "coveroakru": "Масло, натуральный воск",
  "coveroaken": "Decorative impregnating oil, natural wax",
  "coverbeechru": "Масло, натуральный воск",
  "coverbeechen": "Decorative impregnating oil, natural wax",
  "coverbirchru": "Шлифовка",
  "coverbirchen": "Grinding",
  "coverpineru": "Шлифовка",
  "coverpineen": "Grinding",
  "alt": "S115",
  "promoru": null,
  "promoen": null,
  "descriptionru": null,
  "descriptionen": null
}, {
  "item": "S118",
  "h": 17,
  "a": 200,
  "b": 120,
  "r": null,
  "mat": "D",
  "matdef": "D",
  "a2": 185,
  "b2": 105,
  "r2": null,
  "oak": 1,
  "beech": 1,
  "birch": 1,
  "pine": 1,
  "coveroakru": "Масло, натуральный воск",
  "coveroaken": "Decorative impregnating oil, natural wax",
  "coverbeechru": "Масло, натуральный воск",
  "coverbeechen": "Decorative impregnating oil, natural wax",
  "coverbirchru": "Шлифовка",
  "coverbirchen": "Grinding",
  "coverpineru": "Шлифовка",
  "coverpineen": "Grinding",
  "alt": "S118",
  "promoru": null,
  "promoen": null,
  "descriptionru": null,
  "descriptionen": null
}, {
  "item": "S125",
  "h": 17,
  "a": 270,
  "b": 140,
  "r": null,
  "mat": "B",
  "matdef": "B",
  "a2": 255,
  "b2": 125,
  "r2": null,
  "oak": null,
  "beech": 1,
  "birch": 1,
  "pine": 1,
  "coveroakru": "Масло, натуральный воск",
  "coveroaken": "Decorative impregnating oil, natural wax",
  "coverbeechru": "Масло, натуральный воск",
  "coverbeechen": "Decorative impregnating oil, natural wax",
  "coverbirchru": "Шлифовка",
  "coverbirchen": "Grinding",
  "coverpineru": "Шлифовка",
  "coverpineen": "Grinding",
  "alt": "S125",
  "promoru": null,
  "promoen": null,
  "descriptionru": null,
  "descriptionen": null
}, {
  "item": "S130",
  "h": 17,
  "a": 320,
  "b": 170,
  "r": null,
  "mat": "D",
  "matdef": "D",
  "a2": 305,
  "b2": 155,
  "r2": null,
  "oak": 1,
  "beech": 1,
  "birch": 1,
  "pine": 1,
  "coveroakru": "Масло, натуральный воск",
  "coveroaken": "Decorative impregnating oil, natural wax",
  "coverbeechru": "Масло, натуральный воск",
  "coverbeechen": "Decorative impregnating oil, natural wax",
  "coverbirchru": "Шлифовка",
  "coverbirchen": "Grinding",
  "coverpineru": "Шлифовка",
  "coverpineen": "Grinding",
  "alt": "S130",
  "promoru": null,
  "promoen": null,
  "descriptionru": null,
  "descriptionen": null
}, {
  "item": "S135",
  "h": 17,
  "a": 370,
  "b": 170,
  "r": null,
  "mat": "B",
  "matdef": "B",
  "a2": 355,
  "b2": 155,
  "r2": null,
  "oak": null,
  "beech": 1,
  "birch": 1,
  "pine": 1,
  "coveroakru": "Масло, натуральный воск",
  "coveroaken": "Decorative impregnating oil, natural wax",
  "coverbeechru": "Масло, натуральный воск",
  "coverbeechen": "Decorative impregnating oil, natural wax",
  "coverbirchru": "Шлифовка",
  "coverbirchen": "Grinding",
  "coverpineru": "Шлифовка",
  "coverpineen": "Grinding",
  "alt": "S135",
  "promoru": null,
  "promoen": null,
  "descriptionru": null,
  "descriptionen": null
}, {
  "item": "S24",
  "h": 17,
  "a": 60,
  "b": 60,
  "r": null,
  "mat": "D",
  "matdef": "D",
  "a2": 40,
  "b2": 40,
  "r2": null,
  "oak": 1,
  "beech": 1,
  "birch": null,
  "pine": null,
  "coveroakru": "Масло, натуральный воск",
  "coveroaken": "Decorative impregnating oil, natural wax",
  "coverbeechru": "Масло, натуральный воск",
  "coverbeechen": "Decorative impregnating oil, natural wax",
  "coverbirchru": "Шлифовка",
  "coverbirchen": "Grinding",
  "coverpineru": "Шлифовка",
  "coverpineen": "Grinding",
  "alt": "S24",
  "promoru": "Новинка",
  "promoen": "New",
  "descriptionru": null,
  "descriptionen": null
}, {
  "item": "S26",
  "h": 17,
  "a": 80,
  "b": 80,
  "r": null,
  "mat": "D",
  "matdef": "D",
  "a2": 60,
  "b2": 60,
  "r2": null,
  "oak": 1,
  "beech": 1,
  "birch": 1,
  "pine": 1,
  "coveroakru": "Масло, натуральный воск",
  "coveroaken": "Decorative impregnating oil, natural wax",
  "coverbeechru": "Масло, натуральный воск",
  "coverbeechen": "Decorative impregnating oil, natural wax",
  "coverbirchru": "Шлифовка",
  "coverbirchen": "Grinding",
  "coverpineru": "Шлифовка",
  "coverpineen": "Grinding",
  "alt": "S26",
  "promoru": "Новинка",
  "promoen": "New",
  "descriptionru": null,
  "descriptionen": null
}, {
  "item": "S210",
  "h": 17,
  "a": 120,
  "b": 120,
  "r": null,
  "mat": "B",
  "matdef": "B",
  "a2": 100,
  "b2": 100,
  "r2": null,
  "oak": null,
  "beech": 1,
  "birch": null,
  "pine": null,
  "coveroakru": "Масло, натуральный воск",
  "coveroaken": "Decorative impregnating oil, natural wax",
  "coverbeechru": "Масло, натуральный воск",
  "coverbeechen": "Decorative impregnating oil, natural wax",
  "coverbirchru": "Шлифовка",
  "coverbirchen": "Grinding",
  "coverpineru": "Шлифовка",
  "coverpineen": "Grinding",
  "alt": "S210",
  "promoru": "Новинка",
  "promoen": "New",
  "descriptionru": null,
  "descriptionen": null
}, {
  "item": "S212",
  "h": 17,
  "a": 140,
  "b": 100,
  "r": null,
  "mat": "D",
  "matdef": "D",
  "a2": 120,
  "b2": 80,
  "r2": null,
  "oak": 1,
  "beech": 1,
  "birch": 1,
  "pine": 1,
  "coveroakru": "Масло, натуральный воск",
  "coveroaken": "Decorative impregnating oil, natural wax",
  "coverbeechru": "Масло, натуральный воск",
  "coverbeechen": "Decorative impregnating oil, natural wax",
  "coverbirchru": "Шлифовка",
  "coverbirchen": "Grinding",
  "coverpineru": "Шлифовка",
  "coverpineen": "Grinding",
  "alt": "S212",
  "promoru": "Новинка",
  "promoen": "New",
  "descriptionru": null,
  "descriptionen": null
}, {
  "item": "S215",
  "h": 17,
  "a": 170,
  "b": 120,
  "r": null,
  "mat": "B",
  "matdef": "B",
  "a2": 150,
  "b2": 100,
  "r2": null,
  "oak": null,
  "beech": 1,
  "birch": 1,
  "pine": 1,
  "coveroakru": "Масло, натуральный воск",
  "coveroaken": "Decorative impregnating oil, natural wax",
  "coverbeechru": "Масло, натуральный воск",
  "coverbeechen": "Decorative impregnating oil, natural wax",
  "coverbirchru": "Шлифовка",
  "coverbirchen": "Grinding",
  "coverpineru": "Шлифовка",
  "coverpineen": "Grinding",
  "alt": "S215",
  "promoru": null,
  "promoen": null,
  "descriptionru": null,
  "descriptionen": null
}, {
  "item": "S218",
  "h": 17,
  "a": 200,
  "b": 120,
  "r": null,
  "mat": "B",
  "matdef": "B",
  "a2": 180,
  "b2": 100,
  "r2": null,
  "oak": null,
  "beech": 1,
  "birch": 1,
  "pine": 1,
  "coveroakru": "Масло, натуральный воск",
  "coveroaken": "Decorative impregnating oil, natural wax",
  "coverbeechru": "Масло, натуральный воск",
  "coverbeechen": "Decorative impregnating oil, natural wax",
  "coverbirchru": "Шлифовка",
  "coverbirchen": "Grinding",
  "coverpineru": "Шлифовка",
  "coverpineen": "Grinding",
  "alt": "S218",
  "promoru": null,
  "promoen": null,
  "descriptionru": null,
  "descriptionen": null
}, {
  "item": "S220",
  "h": 17,
  "a": 220,
  "b": 170,
  "r": null,
  "mat": "B",
  "matdef": "B",
  "a2": 200,
  "b2": 150,
  "r2": null,
  "oak": null,
  "beech": 1,
  "birch": null,
  "pine": null,
  "coveroakru": "Масло, натуральный воск",
  "coveroaken": "Decorative impregnating oil, natural wax",
  "coverbeechru": "Масло, натуральный воск",
  "coverbeechen": "Decorative impregnating oil, natural wax",
  "coverbirchru": "Шлифовка",
  "coverbirchen": "Grinding",
  "coverpineru": "Шлифовка",
  "coverpineen": "Grinding",
  "alt": "S220",
  "promoru": "Новинка",
  "promoen": "New",
  "descriptionru": null,
  "descriptionen": null
}, {
  "item": "S225",
  "h": 17,
  "a": 270,
  "b": 140,
  "r": null,
  "mat": "B",
  "matdef": "B",
  "a2": 250,
  "b2": 120,
  "r2": null,
  "oak": null,
  "beech": 1,
  "birch": 1,
  "pine": 1,
  "coveroakru": "Масло, натуральный воск",
  "coveroaken": "Decorative impregnating oil, natural wax",
  "coverbeechru": "Масло, натуральный воск",
  "coverbeechen": "Decorative impregnating oil, natural wax",
  "coverbirchru": "Шлифовка",
  "coverbirchen": "Grinding",
  "coverpineru": "Шлифовка",
  "coverpineen": "Grinding",
  "alt": "S225",
  "promoru": null,
  "promoen": null,
  "descriptionru": null,
  "descriptionen": null
}, {
  "item": "S230U",
  "h": 17,
  "a": 320,
  "b": 120,
  "r": null,
  "mat": "B",
  "matdef": "B",
  "a2": 300,
  "b2": 100,
  "r2": null,
  "oak": null,
  "beech": 1,
  "birch": null,
  "pine": null,
  "coveroakru": "Масло, натуральный воск",
  "coveroaken": "Decorative impregnating oil, natural wax",
  "coverbeechru": "Масло, натуральный воск",
  "coverbeechen": "Decorative impregnating oil, natural wax",
  "coverbirchru": "Шлифовка",
  "coverbirchen": "Grinding",
  "coverpineru": "Шлифовка",
  "coverpineen": "Grinding",
  "alt": "S230U",
  "promoru": "Новинка",
  "promoen": "New",
  "descriptionru": null,
  "descriptionen": null
}, {
  "item": "S230",
  "h": 17,
  "a": 320,
  "b": 170,
  "r": null,
  "mat": "B",
  "matdef": "B",
  "a2": 300,
  "b2": 150,
  "r2": null,
  "oak": null,
  "beech": 1,
  "birch": 1,
  "pine": 1,
  "coveroakru": "Масло, натуральный воск",
  "coveroaken": "Decorative impregnating oil, natural wax",
  "coverbeechru": "Масло, натуральный воск",
  "coverbeechen": "Decorative impregnating oil, natural wax",
  "coverbirchru": "Шлифовка",
  "coverbirchen": "Grinding",
  "coverpineru": "Шлифовка",
  "coverpineen": "Grinding",
  "alt": "S230",
  "promoru": null,
  "promoen": null,
  "descriptionru": null,
  "descriptionen": null
}, {
  "item": "S235",
  "h": 17,
  "a": 370,
  "b": 170,
  "r": null,
  "mat": "B",
  "matdef": "B",
  "a2": 350,
  "b2": 150,
  "r2": null,
  "oak": null,
  "beech": 1,
  "birch": 1,
  "pine": 1,
  "coveroakru": "Масло, натуральный воск",
  "coveroaken": "Decorative impregnating oil, natural wax",
  "coverbeechru": "Масло, натуральный воск",
  "coverbeechen": "Decorative impregnating oil, natural wax",
  "coverbirchru": "Шлифовка",
  "coverbirchen": "Grinding",
  "coverpineru": "Шлифовка",
  "coverpineen": "Grinding",
  "alt": "S235",
  "promoru": null,
  "promoen": null,
  "descriptionru": null,
  "descriptionen": null
}, {
  "item": "S255",
  "h": 17,
  "a": 570,
  "b": 170,
  "r": null,
  "mat": "B",
  "matdef": "B",
  "a2": 550,
  "b2": 150,
  "r2": null,
  "oak": null,
  "beech": 1,
  "birch": null,
  "pine": null,
  "coveroakru": "Масло, натуральный воск",
  "coveroaken": "Decorative impregnating oil, natural wax",
  "coverbeechru": "Масло, натуральный воск",
  "coverbeechen": "Decorative impregnating oil, natural wax",
  "coverbirchru": "Шлифовка",
  "coverbirchen": "Grinding",
  "coverpineru": "Шлифовка",
  "coverpineen": "Grinding",
  "alt": "S255",
  "promoru": "Новинка",
  "promoen": "New",
  "descriptionru": null,
  "descriptionen": null
}, {
  "item": "S275",
  "h": 17,
  "a": 770,
  "b": 170,
  "r": null,
  "mat": "B",
  "matdef": "B",
  "a2": 750,
  "b2": 150,
  "r2": null,
  "oak": null,
  "beech": 1,
  "birch": null,
  "pine": null,
  "coveroakru": "Масло, натуральный воск",
  "coveroaken": "Decorative impregnating oil, natural wax",
  "coverbeechru": "Масло, натуральный воск",
  "coverbeechen": "Decorative impregnating oil, natural wax",
  "coverbirchru": "Шлифовка",
  "coverbirchen": "Grinding",
  "coverpineru": "Шлифовка",
  "coverpineen": "Grinding",
  "alt": "S255",
  "promoru": "Новинка",
  "promoen": "New",
  "descriptionru": null,
  "descriptionen": null
}]
